README.md
setup.py
web_llm/__init__.py
web_llm/conversation.py
web_llm/utils.py
web_llm/relax_model/__init__.py
web_llm/relax_model/llama.py
web_llm/transform/__init__.py
web_llm/transform/dispatch_tir_operator.py
web_llm/transform/quantization.py
web_llm/transform/transpose_matmul.py
web_lmm.egg-info/PKG-INFO
web_lmm.egg-info/SOURCES.txt
web_lmm.egg-info/dependency_links.txt
web_lmm.egg-info/requires.txt
web_lmm.egg-info/top_level.txt